unreachable/__init__.py
unreachable-0.1.0.dist-info/LICENSE
unreachable-0.1.0.dist-info/METADATA
unreachable-0.1.0.dist-info/WHEEL
unreachable-0.1.0.dist-info/RECORD
